my_langchain_runtime/__init__.py
my_langchain_runtime/pyarmor_runtime.so
superai_langchain/__init__.py
superai_langchain/text_splitter.py
superai_langchain/agents/__init__.py
superai_langchain/agents/chatglm_functions_agent/__init__.py
superai_langchain/agents/chatglm_functions_agent/base.py
superai_langchain/agents/chatglm_functions_agent/output_parser.py
superai_langchain/agents/chatglm_functions_agent/prompt.py
superai_langchain/agents/llm_functions_agent/__init__.py
superai_langchain/agents/llm_functions_agent/base.py
superai_langchain/autogen_role/__init__.py
superai_langchain/autogen_role/assistant.py
superai_langchain/autogen_role/custom.py
superai_langchain/autogen_role/groupchat_manager.py
superai_langchain/autogen_role/user.py
superai_langchain/chains/__init__.py
superai_langchain/chains/loader_output.py
superai_langchain/chains/transform.py
superai_langchain/chains/autogen/__init__.py
superai_langchain/chains/autogen/auto_gen.py
superai_langchain/chains/combine_documents/__init__.py
superai_langchain/chains/combine_documents/stuff.py
superai_langchain/chains/conversational_retrieval/__init__.py
superai_langchain/chains/conversational_retrieval/base.py
superai_langchain/chains/qa_generation/__init__.py
superai_langchain/chains/qa_generation/base.py
superai_langchain/chains/qa_generation/base_v2.py
superai_langchain/chains/qa_generation/prompt.py
superai_langchain/chains/qa_generation/prompt_v2.py
superai_langchain/chains/question_answering/__init__.py
superai_langchain/chains/retrieval/__init__.py
superai_langchain/chains/retrieval/retrieval_chain.py
superai_langchain/chains/router/__init__.py
superai_langchain/chains/router/multi_rule.py
superai_langchain/chains/router/rule_router.py
superai_langchain/chat_models/__init__.py
superai_langchain/chat_models/host_llm.py
superai_langchain/chat_models/minimax.py
superai_langchain/chat_models/proxy_llm.py
superai_langchain/chat_models/qwen.py
superai_langchain/chat_models/sensetime.py
superai_langchain-122.1.1.5.dist-info/METADATA
superai_langchain-122.1.1.5.dist-info/WHEEL
superai_langchain-122.1.1.5.dist-info/top_level.txt
superai_langchain-122.1.1.5.dist-info/RECORD
