Metadata-Version: 2.4
Name: superai_langchain
Version: 122.1.1.5
Summary: superai langchain modules
Home-page: https://github.com/xxx/superai
Author: Owen
Author-email: contact@Owen.com
License: Apache 2.0
Classifier: Programming Language :: Python :: 3
Classifier: Programming Language :: Python :: 3.6
Classifier: Programming Language :: Python :: 3.7
Classifier: Programming Language :: Python :: 3.8
Classifier: Programming Language :: Python :: 3.9
Classifier: License :: OSI Approved :: Apache Software License
Classifier: Operating System :: OS Independent
Requires-Python: >=3.6
Requires-Dist: langchain==0.3.25
Requires-Dist: langchain-community==0.3.24
Requires-Dist: zhipuai
Requires-Dist: websocket-client
Requires-Dist: elasticsearch
Requires-Dist: opencv-python==4.5.5.64
Requires-Dist: Pillow>=11.0.0
Requires-Dist: jieba==0.42.1
Requires-Dist: pydantic
Requires-Dist: pymupdf==1.23.8
Requires-Dist: shapely==2.0.2
Requires-Dist: filetype==1.2.0
Requires-Dist: langgraph==0.3.27
Requires-Dist: openai==1.93.1
Requires-Dist: langchain_openai==0.3.12
Requires-Dist: llama-index==0.9.48
Requires-Dist: pyjwt==1.7.1
Requires-Dist: fastmcp==2.6.1
Requires-Dist: mcp==1.9.2
Dynamic: author
Dynamic: author-email
Dynamic: classifier
Dynamic: description
Dynamic: description-content-type
Dynamic: home-page
Dynamic: license
Dynamic: requires-dist
Dynamic: requires-python
Dynamic: summary
